moola/__init__.py
moola/ui.py
moola/adaptors/__init__.py
moola/adaptors/adaptor.py
moola/adaptors/dolfin_vector.py
moola/adaptors/dolfin_vector_set.py
moola/adaptors/numpy_vector.py
moola/algorithms/__init__.py
moola/algorithms/bfgs.py
moola/algorithms/hybrid_cg.py
moola/algorithms/newton_cg.py
moola/algorithms/newton_cg_trust_region.py
moola/algorithms/nonlinear_cg.py
moola/algorithms/optimisation_algorithm.py
moola/algorithms/steepest_descent.py
moola/linalg/__init__.py
moola/linalg/linear_functional.py
moola/linalg/vector.py
moola/linesearch/__init__.py
moola/linesearch/armijo.py
moola/linesearch/dcsrch.py
moola/linesearch/dcstep.py
moola/linesearch/fixed.py
moola/linesearch/hager_zhang.py
moola/linesearch/hz_linesearch.py
moola/linesearch/line_search.py
moola/linesearch/strong_wolfe.py
moola/linesearch/dcsrch_fortran/__init__.py
moola/linesearch/dcsrch_fortran/linesearch.py
moola/linesearch/dcsrch_fortran/pymswolfe.py
moola/linesearch/dcsrch_fortran/pyswolfe.py
moola/linesearch/dcsrch_fortran/setup.py
moola/misc/__init__.py
moola/misc/cauchy_point.py
moola/misc/event_counter.py
moola/misc/infinity.py
moola/problem/__init__.py
moola/problem/functional.py
moola/problem/problem.py
moola/problem/solution.py
moola-0.1.6.dist-info/LICENSE
moola-0.1.6.dist-info/METADATA
moola-0.1.6.dist-info/WHEEL
moola-0.1.6.dist-info/top_level.txt
moola-0.1.6.dist-info/RECORD
