Metadata-Version: 2.1
Name: moola
Version: 0.1.6
Summary: Moola optimisation package
Home-page: https://github.com/funsim/moola
Author: Simon Funke
Author-email: simon@simula.no
License: UNKNOWN
Platform: UNKNOWN
Classifier: Programming Language :: Python
Classifier: Programming Language :: Python :: 2
Classifier: Operating System :: OS Independent
Classifier: Environment :: Console
Classifier: Intended Audience :: Science/Research
Classifier: Topic :: Scientific/Engineering :: Mathematics
